blulib/__init__.py
blulib/config_parser/__init__.py
blulib/config_parser/config_parser.py
blulib/config_parser/config_parser_test.py
blulib/config_parser/key_info.py
blulib/config_parser/key_info_test.py
blulib-0.1.2.dist-info/LICENSE
blulib-0.1.2.dist-info/METADATA
blulib-0.1.2.dist-info/WHEEL
blulib-0.1.2.dist-info/top_level.txt
blulib-0.1.2.dist-info/RECORD
